utility.py
api/__init__.py
api/asgi.py
api/settings.py
api/urls.py
api/wsgi.py
api/mapper/__init__.py
api/mapper/admin.py
api/mapper/algo_functions.py
api/mapper/apps.py
api/mapper/models.py
api/mapper/serializers.py
api/mapper/tests.py
api/mapper/views.py
api/mapper/algos/__init__.py
api/mapper/algos/fuzzywuzzy.py
api/mapper/algos/fw_with_openai4.py
api/mapper/algos/harmonizationWithSuggestionService.py
api/mapper/algos/jw_with_openai.py
api/mapper/algos/jw_with_openai4.py
api/mapper/algos/openai.py
api/mapper/algos/openaiGPT4.py
api/mapper/algos/rapidfuzz.py
api/mapper/algos/recursive_harmonization.py
api/mapper/algos/stringmetric.py
data_harmonization_ai_dp-2.0.0.dist-info/METADATA
data_harmonization_ai_dp-2.0.0.dist-info/WHEEL
data_harmonization_ai_dp-2.0.0.dist-info/top_level.txt
data_harmonization_ai_dp-2.0.0.dist-info/RECORD
